[
    {
        "linkBackground": "http://image.phimmoi.net/film/6794/poster.thumb.jpg",
        "linkMovie": "http://www.phimmoi.net/phim/mang-hoang-ky-6794/",
        "engTitle": "The Legend of Jade Sword",
        "title": "Mãng Hoang Kỷ"
    },
    {
        "linkBackground": "http://image.phimmoi.net/film/6790/poster.thumb.jpg",
        "linkMovie": "http://www.phimmoi.net/phim/oi-hoang-de-be-ha-cua-ta-6790/",
        "engTitle": "Oh My Emperor",
        "title": "Ôi Hoàng Đế Bệ Hạ Của Ta"
    },
    {
        "linkBackground": "http://image.phimmoi.net/film/6795/poster.thumb.jpg",
        "linkMovie": "http://www.phimmoi.net/phim/manh-the-thuc-than-6795/",
        "engTitle": "Cinderella Chef",
        "title": "Manh Thê Thực Thần"
    },
    {
        "linkBackground": "http://image.phimmoi.net/film/6672/poster.thumb.jpg",
        "linkMovie": "http://www.phimmoi.net/phim/dai-than-vuong-6672/",
        "engTitle": "Grand Prince",
        "title": "Đại Thân Vương"
    },
    {
        "linkBackground": "http://image.phimmoi.net/film/6771/poster.thumb.jpg",
        "linkMovie": "http://www.phimmoi.net/phim/bach-da-hiep-6771/",
        "engTitle": "Bai Ye Xia",
        "title": "Bạch Dạ Hiệp"
    },
    {
        "linkBackground": "http://image.phimmoi.net/film/6496/poster.thumb.jpg",
        "linkMovie": "http://www.phimmoi.net/phim/phuong-tu-hoang-6496/",
        "engTitle": "Untouchable Lovers",
        "title": "Phượng Tù Hoàng"
    },
    {
        "linkBackground": "http://image.phimmoi.net/film/6693/poster.thumb.jpg",
        "linkMovie": "http://www.phimmoi.net/phim/te-thien-dai-thanh-tran-yeu-quai-6693/",
        "engTitle": "Qi Tian Da Sheng",
        "title": "Tề Thiên Đại Thánh: Trấn Yêu Quái"
    },
    {
        "linkBackground": "http://image.phimmoi.net/film/6522/poster.thumb.jpg",
        "linkMovie": "http://www.phimmoi.net/phim/liet-hoa-nhu-ca-6522/",
        "engTitle": "Liehuo Ruge",
        "title": "Liệt Hỏa Như Ca"
    },
    {
        "linkBackground": "http://image.phimmoi.net/film/6591/poster.thumb.jpg",
        "linkMovie": "http://www.phimmoi.net/phim/tan-tieu-ngao-giang-ho-2018-6591/",
        "engTitle": "New Smiling Proud Wanderer",
        "title": "Tân Tiếu Ngạo Giang Hồ 2018"
    },
    {
        "linkBackground": "http://image.phimmoi.net/film/6616/poster.thumb.jpg",
        "linkMovie": "http://www.phimmoi.net/phim/thuc-son-chien-ky-2-6616/",
        "engTitle": "The Legend of Zu",
        "title": "Thục Sơn Chiến Kỷ 2"
    },
    {
        "linkBackground": "http://image.phimmoi.net/film/6618/poster.thumb.jpg",
        "linkMovie": "http://www.phimmoi.net/phim/tam-quoc-co-mat-6618/",
        "engTitle": "Secrets of Three Kingdoms",
        "title": "Tam Quốc Cơ Mật"
    },
    {
        "linkBackground": "http://image.phimmoi.net/film/6532/poster.thumb.jpg",
        "linkMovie": "http://www.phimmoi.net/phim/phieu-huong-kiem-vu-6532/",
        "engTitle": "The Lost Swordship",
        "title": "Phiêu Hương Kiếm Vũ"
    },
    {
        "linkBackground": "http://image.phimmoi.net/film/6583/poster.thumb.jpg",
        "linkMovie": "http://www.phimmoi.net/phim/quy-trung-my-nhan-6583/",
        "engTitle": "Beauties in the Closet",
        "title": "Quỹ Trung Mỹ Nhân"
    },
    {
        "linkBackground": "http://image.phimmoi.net/film/6253/poster.thumb.jpg",
        "linkMovie": "http://www.phimmoi.net/phim/tan-tam-tan-ky-6253/",
        "engTitle": "A Step into the Past",
        "title": "Tân Tầm Tần Ký"
    },
    {
        "linkBackground": "http://image.phimmoi.net/film/6557/poster.thumb.jpg",
        "linkMovie": "http://www.phimmoi.net/phim/dai-hiep-choi-ga-6557/",
        "engTitle": "Dou Ji Xia",
        "title": "Đại Hiệp Chọi Gà"
    },
    {
        "linkBackground": "http://image.phimmoi.net/film/6555/poster.thumb.jpg",
        "linkMovie": "http://www.phimmoi.net/phim/minh-trieu-cam-y-ve-2-6555/",
        "engTitle": "A Security of the Ming Dynasty 2",
        "title": "Minh Triều Cẩm Y Vệ 2"
    },
    {
        "linkBackground": "http://image.phimmoi.net/film/6489/poster.thumb.jpg",
        "linkMovie": "http://www.phimmoi.net/phim/diem-cot-6489/",
        "engTitle": "Colourful Bone",
        "title": "Diễm Cốt"
    },
    {
        "linkBackground": "http://image.phimmoi.net/film/6401/poster.thumb.jpg",
        "linkMovie": "http://www.phimmoi.net/phim/lang-nha-bang-2-phong-khoi-truong-lam-6401/",
        "engTitle": "Nirvana in Fire 2",
        "title": "Lang Nha Bảng 2: Phong Khởi Trường Lâm"
    },
    {
        "linkBackground": "http://image.phimmoi.net/film/6349/poster.thumb.jpg",
        "linkMovie": "http://www.phimmoi.net/phim/quoc-si-vo-song-hoang-phi-hong-6349/",
        "engTitle": "Fei Hung Wong 2017",
        "title": "Quốc Sĩ Vô Song Hoàng Phi Hồng"
    },
    {
        "linkBackground": "http://image.phimmoi.net/film/6347/poster.thumb.jpg",
        "linkMovie": "http://www.phimmoi.net/phim/quan-su-lien-minh-2-ho-khieu-long-ngam-6347/",
        "engTitle": "The Advisors Alliance 2: Growling Tiger, Roaring Dragon",
        "title": "Quân Sư Liên Minh 2: Hổ Khiếu Long Ngâm"
    },
    {
        "linkBackground": "http://image.phimmoi.net/film/4882/poster.thumb.jpg",
        "linkMovie": "http://www.phimmoi.net/phim/thieu-nien-cam-y-ve-4882/",
        "engTitle": "The Young Imperial Guards",
        "title": "Thiếu niên cẩm y vệ"
    },
    {
        "linkBackground": "http://image.phimmoi.net/film/6345/poster.thumb.jpg",
        "linkMovie": "http://www.phimmoi.net/phim/hoa-ta-hoa-phi-hoa-man-thien-6345/",
        "engTitle": "As Flowers Fade And Fly",
        "title": "Hoa Tạ Hoa Phi Hoa Mạn Thiên"
    },
    {
        "linkBackground": "http://image.phimmoi.net/film/6276/poster.thumb.jpg",
        "linkMovie": "http://www.phimmoi.net/phim/bai-kien-cung-chu-dai-nhan-6276/",
        "engTitle": "Your Highness",
        "title": "Bái Kiến Cung Chủ Đại Nhân"
    },
    {
        "linkBackground": "http://image.phimmoi.net/film/6222/poster.thumb.jpg",
        "linkMovie": "http://www.phimmoi.net/phim/doc-bo-thien-ha-6222/",
        "engTitle": "Rule the World",
        "title": "Độc Bộ Thiên Hạ"
    },
    {
        "linkBackground": "http://image.phimmoi.net/film/6221/poster.thumb.jpg",
        "linkMovie": "http://www.phimmoi.net/phim/tuong-quan-o-tren-ta-o-duoi-6221/",
        "engTitle": "Oh My General",
        "title": "Tướng quân ở trên, ta ở dưới"
    },
    {
        "linkBackground": "http://image.phimmoi.net/film/6277/poster.thumb.jpg",
        "linkMovie": "http://www.phimmoi.net/phim/khai-phong-ky-dam-6277/",
        "engTitle": "Kai Feng Qi Tan",
        "title": "Khai Phong Kỳ Đàm"
    },
    {
        "linkBackground": "http://image.phimmoi.net/film/6341/poster.thumb.jpg",
        "linkMovie": "http://www.phimmoi.net/phim/hang-yeu-ky-an-6341/",
        "engTitle": "Monster Hunt Bao Man",
        "title": "Hàng Yêu Kỳ Án"
    }
]